bioio/__init__.py
bioio/array_like_reader.py
bioio/bio_image.py
bioio/ome_utils.py
bioio/plugins.py
bioio/py.typed
bioio/tests/__init__.py
bioio/tests/conftest.py
bioio/tests/test_array_like_reader.py
bioio/tests/test_bio_image.py
bioio/tests/test_plugins.py
bioio/tests/test_writer.py
bioio/tests/helpers/mock_reader.py
bioio/tests/helpers/mock_writer.py
bioio/writers/__init__.py
bioio-3.2.0.dist-info/licenses/LICENSE
docs/CHANGELOG.rst
docs/CODE_OF_CONDUCT.md
docs/CONTRIBUTING.md
docs/GOVERNANCE.md
docs/MIGRATION.md
docs/MISSION_AND_VALUES.md
docs/OVERVIEW.md
docs/api_reference.rst
docs/conf.py
docs/contributing.rst
docs/developer_resources.rst
docs/index.md
docs/installation.rst
bioio-3.2.0.dist-info/METADATA
bioio-3.2.0.dist-info/WHEEL
bioio-3.2.0.dist-info/top_level.txt
bioio-3.2.0.dist-info/RECORD
