Metadata-Version: 2.4
Name: bioio
Version: 3.2.0
Summary: Image reading, metadata management, and image writing for Microscopy images in Python
Author-email: Eva Maxfield Brown <evamaxfieldbrown@gmail.com>, Dan Toloudis <danielt@alleninstitute.org>
License: BSD License
Project-URL: Homepage, https://github.com/bioio-devs/bioio
Project-URL: Bug Tracker, https://github.com/bioio-devs/bioio/issues
Project-URL: Documentation, https://bioio-devs.github.io/bioio
Project-URL: User Support, https://github.com/bioio-devs/bioio/issues
Classifier: Development Status :: 4 - Beta
Classifier: Natural Language :: English
Classifier: Programming Language :: Python :: 3.10
Classifier: Programming Language :: Python :: 3.11
Classifier: Programming Language :: Python :: 3.12
Classifier: Programming Language :: Python :: 3.13
Requires-Python: >=3.10
License-File: LICENSE
Requires-Dist: bioio-base~=3.2.0
Requires-Dist: dask[array]>=2021.4.1
Requires-Dist: numpy>=1.21.0
Requires-Dist: ome-types[lxml]>=0.4.0
Requires-Dist: semver>=3.0.1
Provides-Extra: lint
Requires-Dist: pre-commit>=2.20.0; extra == "lint"
Provides-Extra: test
Requires-Dist: coverage>=5.1; extra == "test"
Requires-Dist: fsspec[http]>=2022.8.0; extra == "test"
Requires-Dist: pytest>=5.4.3; extra == "test"
Requires-Dist: pytest-cov>=2.9.0; extra == "test"
Requires-Dist: pytest-raises>=0.11; extra == "test"
Requires-Dist: quilt3; extra == "test"
Provides-Extra: docs
Requires-Dist: gitchangelog>=3.0.4; extra == "docs"
Requires-Dist: Sphinx>=8.0.0; extra == "docs"
Requires-Dist: furo>=2022.4.7; extra == "docs"
Requires-Dist: numpydoc; extra == "docs"
Requires-Dist: sphinx-copybutton; extra == "docs"
Requires-Dist: myst-parser>=1.0; extra == "docs"
Requires-Dist: linkify-it-py>=2.0.0; extra == "docs"
Provides-Extra: dev
Requires-Dist: ipython>=8.4.0; extra == "dev"
Dynamic: license-file
